scp_analyzer/__init__.py
scp_analyzer/discover_scps.py
scp_analyzer-0.8.0.dist-info/METADATA
scp_analyzer-0.8.0.dist-info/WHEEL
scp_analyzer-0.8.0.dist-info/entry_points.txt
scp_analyzer-0.8.0.dist-info/licenses/LICENSE
scp_analyzer-0.8.0.dist-info/licenses/NOTICE
scp_analyzer-0.8.0.dist-info/RECORD
